e360_charting/__init__.py
e360_charting/_charts.py
e360_charting/builders.py
e360_charting/common.py
e360_charting/helpers.py
e360_charting/models.py
e360_charting/stylers.py
e360_charting/styles.py
e360_charting/utils.py
e360_charting-1.11.0.dist-info/LICENSE.txt
e360_charting-1.11.0.dist-info/METADATA
e360_charting-1.11.0.dist-info/WHEEL
e360_charting-1.11.0.dist-info/top_level.txt
e360_charting-1.11.0.dist-info/RECORD
