Metadata-Version: 2.1
Name: e360-charting
Version: 1.11.0
Summary: Create charts for E360 Plotly Visualisations.
Author: IQVIA
Author-email: e360pypi@iqvia.com
Classifier: Intended Audience :: Developers
Classifier: License :: OSI Approved :: Apache Software License
Classifier: Operating System :: OS Independent
Classifier: Programming Language :: Python
Classifier: Programming Language :: Python :: 3.7
Classifier: Programming Language :: Python :: 3.8
Classifier: Programming Language :: Python :: 3.9
Classifier: Programming Language :: Python :: 3.10
Requires-Python: >=3.7
License-File: LICENSE.txt
Requires-Dist: marshmallow-dataclass
Requires-Dist: marshmallow-enum
Requires-Dist: typeguard (<3)
Requires-Dist: ujson (<6.0.0)
Provides-Extra: full
Requires-Dist: plotly ; extra == 'full'
Requires-Dist: pandas ; extra == 'full'
